LICENSE
MANIFEST.in
README.md
requirements.txt
setup.py
data_tools/__init__.py
data_tools/alerts.py
data_tools/config.py
data_tools/pipeline.py
data_tools/pyspark.py
data_tools/validation.py
data_tools/io/__init__.py
data_tools/io/db.py
data_tools/utils/schema.py
data_tools/utils/secrets.py
data_tools_moton.egg-info/PKG-INFO
data_tools_moton.egg-info/SOURCES.txt
data_tools_moton.egg-info/dependency_links.txt
data_tools_moton.egg-info/not-zip-safe
data_tools_moton.egg-info/top_level.txt